{
  "packets": {
    "SEND_COMMAND": {
      "fields": {
        "command": "string"
      }
    },
    "COMMAND":{
      "fields": {
        "command": "string"
      }
    },
    "ACK":{
      "fields": {}
    },
    "TS_COMMAND":{
      "fields": {
        "command": "string",
        "parameters": "string"
      }
    },
    "REQUEST_LOG_COMMANDS":{
      "fields": {}
    },
    "CANCEL_EXECUTION":{
      "fields": {}
    },
    "LOG_COMMANDS":{
      "fields": {
        "command": "string"
      }
    },
    "LOG_RESPONSE":{
      "fields": {
        "response": "string"
      }
    },
    "REQUEST_POSITION":{
      "fields": {}
    },
    "POSITION": {
      "fields": {
        "x": "float",
        "y": "float"
      }
    },
    "TRACE_OVER":{
      "fields":{
        "JSON": "string"
      }
    }, 
    "SNAP_SHOT":{
      "fields":{
        "camera": "int"
      }
    },
    "SNAP_SHOT_FLAKE_HUNTED":{
      "fields":{
        "camera": "int"
      }
    },
    "REFRESH_SNAPSHOT":{
      "fields":{
        "camera": "int"
      }
    },
    "REFRESH_SNAPSHOT_FLAKE_HUNTED":{
      "fields":{
        "camera": "int"
      }
    },
    "SCAN_FLAKES": {
      "fields": {
        "directory": "string"
      }
    },
    "DRAW_FLAKES": {
      "fields": {
        "directory": "string"
      }
    },
    "DRAW_FLAKES_RESPONSE": {
      "fields": {
        "response": "string"
      }
    },
    "SCAN_FLAKES_RESPONSE": {
      "fields": {
        "response": "string"
      }
    },
    "GOTO_WAFER_IMAGE": {
      "fields": {
        "bottomLeftXOffset": "float",
        "bottomLeftYOffset": "float",
        "waferNumber": "int",
        "imageNumber": "int",
        "directory": "string"
      }
    },
    

    "MESSAGE":{
      "fields":{
        "message": "string"
      }
    },
    "ERROR": {
      "fields": {
        "code": "int",
        "message": "string"
      }
    }
  }
} 